context_lens/__init__.py
context_lens/config.py
context_lens/errors.py
context_lens/main.py
context_lens/run.py
context_lens/server.py
context_lens/models/__init__.py
context_lens/models/data_models.py
context_lens/models/schemas.py
context_lens/parsers/__init__.py
context_lens/parsers/base.py
context_lens/parsers/generic_chunker.py
context_lens/parsers/init_parsers.py
context_lens/parsers/javascript_parser.py
context_lens/parsers/json_parser.py
context_lens/parsers/markdown_parser.py
context_lens/parsers/python_parser.py
context_lens/parsers/registry.py
context_lens/parsers/rust_parser.py
context_lens/parsers/yaml_parser.py
context_lens/processors/__init__.py
context_lens/processors/content_extractor.py
context_lens/processors/file_readers.py
context_lens/services/__init__.py
context_lens/services/document_service.py
context_lens/services/embedding_service.py
context_lens/storage/__init__.py
context_lens/storage/lancedb_manager.py
context_lens/utils/__init__.py
context_lens/utils/github_handler.py
context_lens/utils/url_fetcher.py
context_lens-0.1.8.dist-info/licenses/LICENSE
context_lens-0.1.8.dist-info/METADATA
context_lens-0.1.8.dist-info/WHEEL
context_lens-0.1.8.dist-info/entry_points.txt
context_lens-0.1.8.dist-info/top_level.txt
context_lens-0.1.8.dist-info/RECORD
