Metadata-Version: 2.4
Name: context-lens
Version: 0.1.8
Summary: Context Lens - Give your LLM glasses to understand meaning, not just read words. Semantic search for AI assistants.
Author-email: Corneliu Croitoru <cornel.croitoru@gmail.com>
License: MIT
Project-URL: Homepage, https://github.com/cornelcroi/context-lens
Project-URL: Repository, https://github.com/cornelcroi/context-lens
Project-URL: Issues, https://github.com/cornelcroi/context-lens/issues
Keywords: mcp,model-context-protocol,semantic-search,vector-database,ai-assistant,llm,embedding,rag,knowledge-base,claude,lancedb
Classifier: Development Status :: 3 - Alpha
Classifier: Intended Audience :: Developers
Classifier: License :: OSI Approved :: MIT License
Classifier: Programming Language :: Python :: 3
Classifier: Programming Language :: Python :: 3.11
Classifier: Programming Language :: Python :: 3.12
Requires-Python: >=3.11
License-File: LICENSE
Requires-Dist: fastmcp>=0.1.0
Requires-Dist: lancedb>=0.3.0
Requires-Dist: sentence-transformers>=2.2.0
Requires-Dist: torch>=2.0.0
Requires-Dist: transformers>=4.21.0
Requires-Dist: numpy>=1.21.0
Requires-Dist: pandas>=1.3.0
Requires-Dist: pyarrow>=10.0.0
Requires-Dist: pyyaml>=6.0
Requires-Dist: aiofiles>=23.0.0
Requires-Dist: chardet>=5.0.0
Requires-Dist: platformdirs>=3.0.0
Provides-Extra: dev
Requires-Dist: pytest>=7.0.0; extra == "dev"
Requires-Dist: pytest-asyncio>=0.21.0; extra == "dev"
Requires-Dist: pytest-cov>=4.0.0; extra == "dev"
Requires-Dist: black>=23.0.0; extra == "dev"
Requires-Dist: isort>=5.12.0; extra == "dev"
Requires-Dist: flake8>=6.0.0; extra == "dev"
Requires-Dist: mypy>=1.0.0; extra == "dev"
Dynamic: license-file
